dorkify/__init__.py
dorkify-3.1.dist-info/METADATA
dorkify-3.1.dist-info/WHEEL
dorkify-3.1.dist-info/top_level.txt
dorkify-3.1.dist-info/RECORD
