Metadata-Version: 2.1
Name: dorkify
Version: 3.1
Summary: A Python library for scraping the Google search engine.
Home-page: https://github.com/probablynothate/dorkify
Author: hate
Author-email: 
License: UNKNOWN
Platform: UNKNOWN
Classifier: Programming Language :: Python :: 3
Classifier: License :: OSI Approved :: MIT License
Classifier: Operating System :: OS Independent
Requires-Python: >=3.6
Requires-Dist: beautifulsoup4 (==4.9.3)
Requires-Dist: requests (==2.25.1)
